{"title":"Non-Euclidean data of GODE","markdown":{"yaml":{"title":"Non-Euclidean data of GODE","author":"SEOYEON CHOI","date":"2023-07-01","categories":["GODE","Non-Euclidean"]},"headingText":"Import","containsRefs":false,"markdown":"\n\n> GODE에서 사용된 Graph signal 예제들에 대한 설명\n\n\n# Esmaple 1. Simple Linear\n\n**Data Information**\n\n- $V=\\{{\\boldsymbol v}_1,\\dots,{\\boldsymbol v}_n\\}:=\\{(x_1,y_2,z_3),\\dots,(x_n,y_n,z_n)\\}$\n    - $r_i= 5 + \\cos(\\frac{12\\pi (i - 1)}{n - 1})$, $\\theta_i= -\\pi + \\frac{{\\pi(n-2)(i - 1)}}{n(n - 1)}$\n    - $x_i = r_i \\cos(\\theta_i)$, $y_i = r_i \\sin(\\theta_i)$, $z_i = 10 \\cdot \\sin(\\frac{{6\\pi \\cdot (i - 1)}}{{n - 1}})$.\n- $W_{i,j} = \\begin{cases} \\exp\\left(-\\frac{\\|{\\boldsymbol v}_i -{\\boldsymbol v}_j\\|^2}{2\\theta^2}\\right) & \\|{\\boldsymbol v}_i -{\\boldsymbol v}_j\\|^2 \\le \\kappa \\\\ 0 & o.w\\end{cases}$\n\n> Note that ${\\bf L}$ is GSO, and in this case, GFT is just Discrete Fourier Transform also note that ${\\cal G}_W$ is a regular graph since ${\\bf D}={\\bf I}$. Thus this data is Euclidean data. \n\n**graph signal**\n\n**$y:V \\to \\mathbb{R}$**\n\n- $y_i=\\frac{10}{n}v_i+\\eta_i+\\epsilon_i$ \n- $\\epsilon_i \\sim N(\\mu,\\sigma^2)$\n- $\\eta_i \\sim U^\\star$ with sparsity $0.05$ where $U^\\star$ is mixture of $U(1.5,2)$ and $U(-2,-1.5)$. \n\n> Note that ${\\bf y}$ is weakly stationary ***w.r.t.*** ${\\bf L}$.\n\n**Euclidean Data**\n\n- domain 이 $x$축(실수 $\\mathbb{R}$로 정의되는)인 유클리디안 데이터\n- underline이 선, 아래에서는 $y=5x$가 되겠다.\n    - 1d-grid로 볼 수 있음.([non-euclidean vs euclidean 참고](https://seoyeonc.github.io/sy_hub/posts/2_Studies/GRAPH/2023-07-01-Euclidean_nonEuclidean.html))\n- underliying function이 regular graph로 정의([regular graph 참고](https://seoyeonc.github.io/sy_hub/posts/2_Studies/GRAPH/2023-06-30-Regular%20Graph.html))\n\n![Figure: First example of GODE](Figs/GODE_fig1.png){width=80%}\n\n# Esmaple 2. Orbit\n\n**Data Information**\n\n**${\\cal G}_W=(V,E,{\\bf W})$**\n\n- $V=\\{{\\boldsymbol v}_1,\\dots,{\\boldsymbol v}_n\\}:=\\{(x_1,y_2,z_3),\\dots,(x_n,y_n,z_n)\\}$\n    - $r_i= 5 + \\cos(\\frac{12\\pi (i - 1)}{n - 1})$, $\\theta_i= -\\pi + \\frac{{\\pi(n-2)(i - 1)}}{n(n - 1)}$\n    - $x_i = r_i \\cos(\\theta_i)$, $y_i = r_i \\sin(\\theta_i)$, $z_i = 10 \\cdot \\sin(\\frac{{6\\pi \\cdot (i - 1)}}{{n - 1}})$.\n- $W_{i,j} = \\begin{cases} \\exp\\left(-\\frac{\\|{\\boldsymbol v}_i -{\\boldsymbol v}_j\\|^2}{2\\theta^2}\\right) & \\|{\\boldsymbol v}_i -{\\boldsymbol v}_j\\|^2 \\le \\kappa \\\\ 0 & o.w\\end{cases}$\n\n**Non-Euclidean Data**\n\n- 2D shape이다.\n- domain이 곡선인 논유클리디안 데이터\n- underlying function이 regular graph로 정의되지 않는다.([regular graph 참고](https://seoyeonc.github.io/sy_hub/posts/2_Studies/GRAPH/2023-06-30-Regular%20Graph.html))\n- 거리 계산을 유클리드 거리로 할 때, underline이 곡선이라 합리적이지 않다.\n- weight은 유클리디안 거리로 정의되어 있지만, $\\kappa$로 hyperparameter 지정해주어 거리가 짧으면 유클리디안 거리로 정의하고, 멀면 0으로 연결을 끊는 행렬으로 정의.\n\n::: {.callout-note}\n**유클리디안으로 보고 싶다면??**\n\n- 모든 연결 weight를 끊어버리면 된다.\n- 그러면 regular graph 로 정의 가능.\n- 하지만, d연구의 목적에 어긋남.\n:::\n\n> Note that ${\\bf W}$ is GSO, since ${\\bf W}^\\top = {\\bf W}$. In this cases, ${\\cal G}_W$ is not regular since there does not exist $k$ such that ${\\bf D}=k{\\bf I}$.\n\n**graph signal**\n**${\\bf y}:V \\to \\mathbb{R}^3$**\n\n- ${\\bf y}_i={\\boldsymbol v}_i+{\\boldsymbol \\eta}_i+{\\boldsymbol \\epsilon}_i$ \n- ${\\boldsymbol \\epsilon}_i \\sim N({\\boldsymbol \\mu},\\sigma^2{\\bf I})$\n- ${\\boldsymbol \\eta}_i \\sim U^\\star$ with sparsity $0.05$ where $U^\\star$ is mixture of $U(5,7)$ and $U(-7,-5)$. \n\n> Clearly ${\\bf y}$ is stationary **w.r.t.** ${\\bf W}$ or ${\\bf L}$.\n\n![Figure: Second example of GODE](Figs/GODE_fig2.png){width=80%}\n\n# Esmaple 3. Stanford Bunny\n\n**Data Information**\n\n**pygsp** 라이브러리를 사용하여 데이터 가져옴, weight도!(mesh 로 색의 퍼짐 정도로 나타낸 것으로 간단 이해)\n\n**Non-Euclidean Data**\n\n- 3D shape\n- domain이 곡면이고, underline이 곡면인 넌유클리디안 데이터\n- underlying function 이 색\n    - 아래를 설명해보자면, 연한 파란-연한 초록 점이 언더라인 펑션으로 형성되어 있을때, 진한 색의 점들이 noise로 형성되어 있음.\n- underline이 곡면이라 유클리디안 거리를 사용하는 것이 합리적이지 않다.\n\n![Figure: Third example of GODE](Figs/GODE_fig3.png){width=80%}\n\n# Real data. Earthquake\n\n**Data Information**\n\nThis data is actual data collected from USGS^[https://www.usgs.gov/programs/earthquake-hazards/lists-maps-and-statistics] during the period from 2010 to 2014.\n\n***${\\cal G}=(V,E)$***\n\n- $V=\\{{\\boldsymbol v}_1,\\dots,{\\boldsymbol v}_n\\}$ where ${\\boldsymbol v}:=({\\tt Latitude},{\\tt Longitude})$\n- $W_{i,j} = \\begin{cases} \\exp(-\\frac{\\rho(i,j)}{2\\theta^2}) & if \\rho(i,j) \\le \\kappa \\\\ 0 & o.w. \\end{cases}$ \n    - Here, $\\rho(i,j)=hs({\\boldsymbol v}_i, {\\boldsymbol v}_j)$ is Haversine distance between ${\\boldsymbol v}_i, {\\boldsymbol v}_j$. \n\n- $y_i$ = magnitude\n\n\n**Non-Euclidean Data**\n\n- domain이 곡면이고, underline이 곡면인 넌유클리디안 데이터\n- underlying function 이 magnitude(지진 강도)\n- [haversine](https://en.wikipedia.org/wiki/Haversine_formula) 이용하면 곡면 거리가 이미 포함되어 있지만, 자료가 너무 많아 거리가 먼 연결을 끊어주는 역할로 hyperparameter인 $\\kappa$사용하였다.\n","srcMarkdownNoYaml":"\n\n> GODE에서 사용된 Graph signal 예제들에 대한 설명\n\n# Import\n\n# Esmaple 1. Simple Linear\n\n**Data Information**\n\n- $V=\\{{\\boldsymbol v}_1,\\dots,{\\boldsymbol v}_n\\}:=\\{(x_1,y_2,z_3),\\dots,(x_n,y_n,z_n)\\}$\n    - $r_i= 5 + \\cos(\\frac{12\\pi (i - 1)}{n - 1})$, $\\theta_i= -\\pi + \\frac{{\\pi(n-2)(i - 1)}}{n(n - 1)}$\n    - $x_i = r_i \\cos(\\theta_i)$, $y_i = r_i \\sin(\\theta_i)$, $z_i = 10 \\cdot \\sin(\\frac{{6\\pi \\cdot (i - 1)}}{{n - 1}})$.\n- $W_{i,j} = \\begin{cases} \\exp\\left(-\\frac{\\|{\\boldsymbol v}_i -{\\boldsymbol v}_j\\|^2}{2\\theta^2}\\right) & \\|{\\boldsymbol v}_i -{\\boldsymbol v}_j\\|^2 \\le \\kappa \\\\ 0 & o.w\\end{cases}$\n\n> Note that ${\\bf L}$ is GSO, and in this case, GFT is just Discrete Fourier Transform also note that ${\\cal G}_W$ is a regular graph since ${\\bf D}={\\bf I}$. Thus this data is Euclidean data. \n\n**graph signal**\n\n**$y:V \\to \\mathbb{R}$**\n\n- $y_i=\\frac{10}{n}v_i+\\eta_i+\\epsilon_i$ \n- $\\epsilon_i \\sim N(\\mu,\\sigma^2)$\n- $\\eta_i \\sim U^\\star$ with sparsity $0.05$ where $U^\\star$ is mixture of $U(1.5,2)$ and $U(-2,-1.5)$. \n\n> Note that ${\\bf y}$ is weakly stationary ***w.r.t.*** ${\\bf L}$.\n\n**Euclidean Data**\n\n- domain 이 $x$축(실수 $\\mathbb{R}$로 정의되는)인 유클리디안 데이터\n- underline이 선, 아래에서는 $y=5x$가 되겠다.\n    - 1d-grid로 볼 수 있음.([non-euclidean vs euclidean 참고](https://seoyeonc.github.io/sy_hub/posts/2_Studies/GRAPH/2023-07-01-Euclidean_nonEuclidean.html))\n- underliying function이 regular graph로 정의([regular graph 참고](https://seoyeonc.github.io/sy_hub/posts/2_Studies/GRAPH/2023-06-30-Regular%20Graph.html))\n\n![Figure: First example of GODE](Figs/GODE_fig1.png){width=80%}\n\n# Esmaple 2. Orbit\n\n**Data Information**\n\n**${\\cal G}_W=(V,E,{\\bf W})$**\n\n- $V=\\{{\\boldsymbol v}_1,\\dots,{\\boldsymbol v}_n\\}:=\\{(x_1,y_2,z_3),\\dots,(x_n,y_n,z_n)\\}$\n    - $r_i= 5 + \\cos(\\frac{12\\pi (i - 1)}{n - 1})$, $\\theta_i= -\\pi + \\frac{{\\pi(n-2)(i - 1)}}{n(n - 1)}$\n    - $x_i = r_i \\cos(\\theta_i)$, $y_i = r_i \\sin(\\theta_i)$, $z_i = 10 \\cdot \\sin(\\frac{{6\\pi \\cdot (i - 1)}}{{n - 1}})$.\n- $W_{i,j} = \\begin{cases} \\exp\\left(-\\frac{\\|{\\boldsymbol v}_i -{\\boldsymbol v}_j\\|^2}{2\\theta^2}\\right) & \\|{\\boldsymbol v}_i -{\\boldsymbol v}_j\\|^2 \\le \\kappa \\\\ 0 & o.w\\end{cases}$\n\n**Non-Euclidean Data**\n\n- 2D shape이다.\n- domain이 곡선인 논유클리디안 데이터\n- underlying function이 regular graph로 정의되지 않는다.([regular graph 참고](https://seoyeonc.github.io/sy_hub/posts/2_Studies/GRAPH/2023-06-30-Regular%20Graph.html))\n- 거리 계산을 유클리드 거리로 할 때, underline이 곡선이라 합리적이지 않다.\n- weight은 유클리디안 거리로 정의되어 있지만, $\\kappa$로 hyperparameter 지정해주어 거리가 짧으면 유클리디안 거리로 정의하고, 멀면 0으로 연결을 끊는 행렬으로 정의.\n\n::: {.callout-note}\n**유클리디안으로 보고 싶다면??**\n\n- 모든 연결 weight를 끊어버리면 된다.\n- 그러면 regular graph 로 정의 가능.\n- 하지만, d연구의 목적에 어긋남.\n:::\n\n> Note that ${\\bf W}$ is GSO, since ${\\bf W}^\\top = {\\bf W}$. In this cases, ${\\cal G}_W$ is not regular since there does not exist $k$ such that ${\\bf D}=k{\\bf I}$.\n\n**graph signal**\n**${\\bf y}:V \\to \\mathbb{R}^3$**\n\n- ${\\bf y}_i={\\boldsymbol v}_i+{\\boldsymbol \\eta}_i+{\\boldsymbol \\epsilon}_i$ \n- ${\\boldsymbol \\epsilon}_i \\sim N({\\boldsymbol \\mu},\\sigma^2{\\bf I})$\n- ${\\boldsymbol \\eta}_i \\sim U^\\star$ with sparsity $0.05$ where $U^\\star$ is mixture of $U(5,7)$ and $U(-7,-5)$. \n\n> Clearly ${\\bf y}$ is stationary **w.r.t.** ${\\bf W}$ or ${\\bf L}$.\n\n![Figure: Second example of GODE](Figs/GODE_fig2.png){width=80%}\n\n# Esmaple 3. Stanford Bunny\n\n**Data Information**\n\n**pygsp** 라이브러리를 사용하여 데이터 가져옴, weight도!(mesh 로 색의 퍼짐 정도로 나타낸 것으로 간단 이해)\n\n**Non-Euclidean Data**\n\n- 3D shape\n- domain이 곡면이고, underline이 곡면인 넌유클리디안 데이터\n- underlying function 이 색\n    - 아래를 설명해보자면, 연한 파란-연한 초록 점이 언더라인 펑션으로 형성되어 있을때, 진한 색의 점들이 noise로 형성되어 있음.\n- underline이 곡면이라 유클리디안 거리를 사용하는 것이 합리적이지 않다.\n\n![Figure: Third example of GODE](Figs/GODE_fig3.png){width=80%}\n\n# Real data. Earthquake\n\n**Data Information**\n\nThis data is actual data collected from USGS^[https://www.usgs.gov/programs/earthquake-hazards/lists-maps-and-statistics] during the period from 2010 to 2014.\n\n***${\\cal G}=(V,E)$***\n\n- $V=\\{{\\boldsymbol v}_1,\\dots,{\\boldsymbol v}_n\\}$ where ${\\boldsymbol v}:=({\\tt Latitude},{\\tt Longitude})$\n- $W_{i,j} = \\begin{cases} \\exp(-\\frac{\\rho(i,j)}{2\\theta^2}) & if \\rho(i,j) \\le \\kappa \\\\ 0 & o.w. \\end{cases}$ \n    - Here, $\\rho(i,j)=hs({\\boldsymbol v}_i, {\\boldsymbol v}_j)$ is Haversine distance between ${\\boldsymbol v}_i, {\\boldsymbol v}_j$. \n\n- $y_i$ = magnitude\n\n\n**Non-Euclidean Data**\n\n- domain이 곡면이고, underline이 곡면인 넌유클리디안 데이터\n- underlying function 이 magnitude(지진 강도)\n- [haversine](https://en.wikipedia.org/wiki/Haversine_formula) 이용하면 곡면 거리가 이미 포함되어 있지만, 자료가 너무 많아 거리가 먼 연결을 끊어주는 역할로 hyperparameter인 $\\kappa$사용하였다.\n"},"formats":{"html":{"identifier":{"display-name":"HTML","target-format":"html","base-format":"html"},"execute":{"fig-width":7,"fig-height":5,"fig-format":"retina","fig-dpi":96,"df-print":"default","error":false,"eval":true,"cache":null,"freeze":true,"echo":true,"output":true,"warning":true,"include":true,"keep-md":false,"keep-ipynb":false,"ipynb":null,"enabled":false,"daemon":null,"daemon-restart":false,"debug":false,"ipynb-filters":[],"ipynb-shell-interactivity":null,"plotly-connected":true,"engine":"jupyter"},"render":{"keep-tex":false,"keep-typ":false,"keep-source":false,"keep-hidden":false,"prefer-html":false,"output-divs":true,"output-ext":"html","fig-align":"default","fig-pos":null,"fig-env":null,"code-fold":false,"code-overflow":"scroll","code-link":false,"code-line-numbers":false,"code-tools":false,"tbl-colwidths":"auto","merge-includes":true,"inline-includes":false,"preserve-yaml":false,"latex-auto-mk":true,"latex-auto-install":true,"latex-clean":true,"latex-min-runs":1,"latex-max-runs":10,"latex-makeindex":"makeindex","latex-makeindex-opts":[],"latex-tlmgr-opts":[],"latex-input-paths":[],"latex-output-dir":null,"link-external-icon":false,"link-external-newwindow":false,"self-contained-math":false,"format-resources":[],"notebook-links":true},"pandoc":{"standalone":true,"wrap":"none","default-image-extension":"png","to":"html","css":["../../styles.css"],"toc":true,"output-file":"2023-07-01-NonEuclidean_data_of_GODE.html"},"language":{"toc-title-document":"Table of contents","toc-title-website":"On this page","related-formats-title":"Other Formats","related-notebooks-title":"Notebooks","source-notebooks-prefix":"Source","other-links-title":"Other Links","code-links-title":"Code Links","launch-dev-container-title":"Launch Dev Container","launch-binder-title":"Launch Binder","article-notebook-label":"Article Notebook","notebook-preview-download":"Download Notebook","notebook-preview-download-src":"Download Source","notebook-preview-back":"Back to Article","manuscript-meca-bundle":"MECA Bundle","section-title-abstract":"Abstract","section-title-appendices":"Appendices","section-title-footnotes":"Footnotes","section-title-references":"References","section-title-reuse":"Reuse","section-title-copyright":"Copyright","section-title-citation":"Citation","appendix-attribution-cite-as":"For attribution, please cite this work as:","appendix-attribution-bibtex":"BibTeX citation:","title-block-author-single":"Author","title-block-author-plural":"Authors","title-block-affiliation-single":"Affiliation","title-block-affiliation-plural":"Affiliations","title-block-published":"Published","title-block-modified":"Modified","title-block-keywords":"Keywords","callout-tip-title":"Tip","callout-note-title":"Note","callout-warning-title":"Warning","callout-important-title":"Important","callout-caution-title":"Caution","code-summary":"Code","code-tools-menu-caption":"Code","code-tools-show-all-code":"Show All Code","code-tools-hide-all-code":"Hide All Code","code-tools-view-source":"View Source","code-tools-source-code":"Source Code","code-line":"Line","code-lines":"Lines","copy-button-tooltip":"Copy to Clipboard","copy-button-tooltip-success":"Copied!","repo-action-links-edit":"Edit this page","repo-action-links-source":"View source","repo-action-links-issue":"Report an issue","back-to-top":"Back to top","search-no-results-text":"No results","search-matching-documents-text":"matching documents","search-copy-link-title":"Copy link to search","search-hide-matches-text":"Hide additional matches","search-more-match-text":"more match in this document","search-more-matches-text":"more matches in this document","search-clear-button-title":"Clear","search-text-placeholder":"","search-detached-cancel-button-title":"Cancel","search-submit-button-title":"Submit","search-label":"Search","toggle-section":"Toggle section","toggle-sidebar":"Toggle sidebar navigation","toggle-dark-mode":"Toggle dark mode","toggle-reader-mode":"Toggle reader mode","toggle-navigation":"Toggle navigation","crossref-fig-title":"Figure","crossref-tbl-title":"Table","crossref-lst-title":"Listing","crossref-thm-title":"Theorem","crossref-lem-title":"Lemma","crossref-cor-title":"Corollary","crossref-prp-title":"Proposition","crossref-cnj-title":"Conjecture","crossref-def-title":"Definition","crossref-exm-title":"Example","crossref-exr-title":"Exercise","crossref-ch-prefix":"Chapter","crossref-apx-prefix":"Appendix","crossref-sec-prefix":"Section","crossref-eq-prefix":"Equation","crossref-lof-title":"List of Figures","crossref-lot-title":"List of Tables","crossref-lol-title":"List of Listings","environment-proof-title":"Proof","environment-remark-title":"Remark","environment-solution-title":"Solution","listing-page-order-by":"Order By","listing-page-order-by-default":"Default","listing-page-order-by-date-asc":"Oldest","listing-page-order-by-date-desc":"Newest","listing-page-order-by-number-desc":"High to Low","listing-page-order-by-number-asc":"Low to High","listing-page-field-date":"Date","listing-page-field-title":"Title","listing-page-field-description":"Description","listing-page-field-author":"Author","listing-page-field-filename":"File Name","listing-page-field-filemodified":"Modified","listing-page-field-subtitle":"Subtitle","listing-page-field-readingtime":"Reading Time","listing-page-field-wordcount":"Word Count","listing-page-field-categories":"Categories","listing-page-minutes-compact":"{0} min","listing-page-category-all":"All","listing-page-no-matches":"No matching items","listing-page-words":"{0} words"},"metadata":{"lang":"en","fig-responsive":true,"quarto-version":"1.4.527","theme":{"light":"flatly"},"code-copy":false,"title-block-banner":true,"title":"Non-Euclidean data of GODE","author":"SEOYEON CHOI","date":"2023-07-01","categories":["GODE","Non-Euclidean"]},"extensions":{"book":{"multiFile":true}}}},"projectFormats":["html"]}